{
  "name": "Scawtite (Ca₇(Si₆O₁₈)CO₃-2H₂O)",
  "description": "A hydrous calcium-silicate mineral with carbonate. Reference: Si29 tensor parameters, Hansen et al. DOI: 10.1021/ic020647f",
  "isotopomers": [
    {
      "name": "Q2 (1)",
      "sites": [
        {
          "isotope": "29Si",
          "isotropic_chemical_shift": "-85.1 ppm",
          "shielding_symmetric": {
            "zeta": "-49.1 ppm",
            "eta": 0.7
          }
        }
      ],
      "abundance": "100 %"
    },
    {
      "name": "Q2 (2)",
      "sites": [
        {
          "isotope": "29Si",
          "isotropic_chemical_shift": "-86.5 ppm",
          "shielding_symmetric": {
            "zeta": "-61.1 ppm",
            "eta": 0.66
          }
        }
      ],
      "abundance": "100 %"
    }
  ]
}
